CHANGES.rst
CONTRIBUTORS.rst
MANIFEST.in
README.rst
setup.cfg
setup.py
Products/__init__.py
Products.windowZ.egg-info/PKG-INFO
Products.windowZ.egg-info/SOURCES.txt
Products.windowZ.egg-info/dependency_links.txt
Products.windowZ.egg-info/entry_points.txt
Products.windowZ.egg-info/namespace_packages.txt
Products.windowZ.egg-info/not-zip-safe
Products.windowZ.egg-info/requires.txt
Products.windowZ.egg-info/top_level.txt
Products/windowZ/WindowZTool.py
Products/windowZ/__init__.py
Products/windowZ/config.py
Products/windowZ/configure.zcml
Products/windowZ/controlpanel.py
Products/windowZ/interfaces.py
Products/windowZ/tool.gif
Products/windowZ/upgrades.py
Products/windowZ/upgrades.zcml
Products/windowZ/content/Window.py
Products/windowZ/content/__init__.py
Products/windowZ/i18n/generated.pot
Products/windowZ/i18n/manual.pot
Products/windowZ/i18n/rebuild_i18n.sh
Products/windowZ/i18n/usei18ndude.sh
Products/windowZ/i18n/windowZ-da.po
Products/windowZ/i18n/windowZ-de.po
Products/windowZ/i18n/windowZ-es.po
Products/windowZ/i18n/windowZ-fr.po
Products/windowZ/i18n/windowZ-it.po
Products/windowZ/i18n/windowZ-nl.po
Products/windowZ/i18n/windowZ-plone-da.po
Products/windowZ/i18n/windowZ-plone-de.po
Products/windowZ/i18n/windowZ-plone-es.po
Products/windowZ/i18n/windowZ-plone-fr.po
Products/windowZ/i18n/windowZ-plone-it.po
Products/windowZ/i18n/windowZ-plone-nl.po
Products/windowZ/i18n/windowZ-plone-pt-br.po
Products/windowZ/i18n/windowZ-plone-pt.po
Products/windowZ/i18n/windowZ-plone.pot
Products/windowZ/i18n/windowZ-pt-br.po
Products/windowZ/i18n/windowZ-pt.po
Products/windowZ/i18n/windowZ.pot
Products/windowZ/model/cleanup.sh
Products/windowZ/model/generate.conf
Products/windowZ/model/generate.sh
Products/windowZ/model/windowZ.png
Products/windowZ/model/windowZ.zuml
Products/windowZ/profiles/default/controlpanel.xml
Products/windowZ/profiles/default/metadata.xml
Products/windowZ/profiles/default/registry.xml
Products/windowZ/profiles/default/skins.xml
Products/windowZ/profiles/default/types.xml
Products/windowZ/profiles/default/skins/custom.xml
Products/windowZ/profiles/default/types/.directory
Products/windowZ/profiles/default/types/Window.xml
Products/windowZ/skins/windowZ/window_both_view.pt
Products/windowZ/skins/windowZ/window_both_view.pt.metadata
