Metadata-Version: 2.1
Name: Products.windowZ
Version: 2.0.1
Summary: Show web-pages inside an iframe. Plone content-type.
Home-page: http://plone.org/products/windowz
Author: Jean Rodrigo Ferri
Author-email: jeanrodrigoferri@yahoo.com.br
License: GPL
Keywords: plone layout composition themeing
Platform: UNKNOWN
Classifier: Development Status :: 6 - Mature
Classifier: Environment :: Web Environment
Classifier: Framework :: Plone
Classifier: Framework :: Plone :: 5.0
Classifier: License :: OSI Approved :: GNU General Public License (GPL)
Classifier: Operating System :: OS Independent
Classifier: Programming Language :: Python
Classifier: Programming Language :: Python :: 2.7
Classifier: Topic :: Software Development :: Libraries :: Python Modules
Provides-Extra: test
